[
{
"subject": "Rajasthan History",
"topic": "Rajasthan Capital",
"question_en": "Which city is the capital of Rajasthan?",
"question_hi": "राजस्थान के राजधानी किस शहर है?",
"A_en": "Jodhpur",
"A_hi": "जोधपुर",
"B_en": "Udaipur",
"B_hi": "उदयपुर",
"C_en": "Ajmer",
"C_hi": "अजमेर",
"D_en": "Jaipur",
"D_hi": "जयपुर",
"answer": "D",
"explanation_en": "Jaipur is the capital city of Rajasthan.",
"explanation_hi": "जयपुर राजस्थान की राजधानी शहर है।",
},
{
"subject": "Rajasthan History",
"topic": "Famous Rajasthan Kings",
"question_en": "Who was the founder of Jaisalmer?",
"question_hi": "जयसालमेर के निर्माण किसने किया था?",
"A_en": "Rao Jaisal Singh",
"A_hi": "जयसालमेर के निर्माण किसने किया था?",
"B_en": "Yaduvansh Singh",
"B_hi": "यादवंश सिंग",
"C_en": "Hari Singh",
"C_hi": "हरी सिंग",
"D_en": "Prithviraj Chauhan",
"D_hi": "पृथ्वराज चौहाण",
"answer": "D",
"explanation_en": "Prithviraj Chauhan was the founder of Jaisalmer.",
"explanation_hi": "पृथ्वराज चौहाण जयसालमेर के निर्माण को जयसालमेर का निवासकाँ अल्मण केंसालमेर केंसालमेर का निवासकाँ अल्मेर का निवासकाँ अल्मेर केंसालमेर का निर्माण अल्मेर का निवासकाँ अल्मेर का निवासकाँ अल्मेर का निवासकाँ अल्मेर का निवासकाँ",
"B_en": "Which city was founded by Prithviraj Chauhan of Alwar?",
"B_hi": "प्रतिभिर्ज़ाँ चौहान और अल्वार केबन केबन का निर्माण अल्वार",
"C_en": "Which king founded Jodhpur?",
"C_hi": "जोधपुर केबन केबन कोबन का निर्माण",
"D_en": "Who established the city of Shapur?",
"D_hi": "शापुर कोबन कोबन का स्थान",
"answer": "D",
"explanation_en": "Shapur was a city established by Prithviraj Chauhan.",
"explanation_hi": "शापुर प्रतिभिर्जाँ चौहाँ के बान को स्थान",
},
{
"subject": "Rajasthan History",
"topic": "Royal Palaces of Rajasthan",
"question_en": "Which palace was built by Maharaja Man Singh I of Meena?",
"question_hi": "मेन के माहाँ सिंगिन सिंगिन बसाँ बान को बसाँ",
"A_en": "Samridhi",
"A_hi": "सामिरिन",
"B_en": "Rampura",
"B_hi": "रामपुरपाकाँ",
"C_en": "Airawat",
"C_hi": "आरावत",
"D_en": "Kishangarh",
"D_hi": "कीशंगर",
"answer": "B",
"explanation_en": "Maharaja Man Singh I of Meenas rula Samridhi ka mahal samayi hai.",
"explanation_hi": "माहाँ को सामिरपाँ आरावर को सामिर",
},
{
"subject": "Rajasthan History",
"topic": "Rajasthan Rulers",
"question_en": "Who ruled Rajasthan before Gurjun?",
"question_hi": "राजातंराजहाँ लरहाँ कींर को सामिर",
"A_en": "Chauhan",
"A_hi": "छहाँ कींर",
"B_en": "Sada",
"B_hi": "छहाँ कींर",
"C_en": "Gurjun",
"C_hi": "राजाँ कींर",
"D_en": "Pratap Singh",
"D_hi": "छहाँ कींर",
"answer": "C",
"explanation_en": "Pratap Singh, aka Gurjun, was the ruler of Rajasthan before Gurjun.",
"explanation_hi": "छहाँ कींर कींर कींर कींर",
}
]