[
{
"subject": "Rajasthan History",
"topic": "",
"question_en": "Which historical fort is located in Jaipur?",
"question_hi": "जयपुर में कौन सी धारा है ?",
"A_en": "Amber Fort", "A_hi": "आमरन धारा",
"B_en": "Hawa Mahal", "B_hi": "हावा महाल",
"C_en": "Gaitor", "C_hi": "गाईटोर",
"D_en": "Pratapgarh Fort", "D_hi": "प्रतापगढ़ धारा",
"answer": "B",
"explanation_en": "Hawa Mahal is a historical monument located in Jaipur, known for its unique architecture.",
"explanation_hi": "हावा महाल जैसेवालियों में रजस्तान के भरती प्रमाण है।",
"explanation_hi": "हावा महाल है जैसेवालियों में रजस्तान के भरती प्रमाण है।",
"A_hi": "राजस्तान",
"B_hi": "हावा महाल",
"C_hi": "जैसेवालियों",
"D_hi": "भरती प्रमाण",
"question_en": "Which historical monument is located in Jaipur?",
"question_hi": "जैसेवालियों में राजस्तान के भरती प्रमाण",
"answer": "A",
"explanation_en": "Amber Fort is a historical monument located in Jaipur, known for its intricate architecture.",
"explanation_hi": "आंबर फोट जैसेवालियों में राजस्तान के भरती प्रमाण",
"A_hi": "आंबर फोट",
"B_hi": "जैसेवालियों",
"C_hi": "राजस्तान",
"D_hi": "भरती प्रमाण",
"question_en": "Which historical monument is surrounded by a seven-tiered gate?",
"question_hi": "आंबर फोट के भागे सांचित सपैंक के बाहर है।",
"answer": "A",
"explanation_en": "Amber Fort in Jaipur is surrounded by a seven-tiered gate.",
"explanation_hi": "आंबर फोट, जैसेवालियों में सपैंक के बाहर है।",
"A_en": "Amber Fort",
"B_en": "Jaipur",
"C_en": "Seven Gates",
"D_en": "History",
"question_en": "Which is the main entrance to Amber Fort?",
"question_hi": "आंबर फोट का मुखत्ता कौन है?",
"answer": "A",
"explanation_en": "The main entrance to Amber Fort is the 'Ganesh Pol' also known as 'Durgapol'.",
"explanation_hi": "आंबर फोट का मुखत्ता क्लोड़ मोटियों में मुखत्ता कौन है?",
"A_en": "Ganesh Pol (Durgapol)",
"B_en": "Amer Fort",
"C_en": "Jaigarh Fort",
"D_en": "Meera Pol",
"question_en": "Which of the following forts was built by the Rajput ruler Jai Singh II?",
"question_hi": "निवारी मोटियों में मैं में मैन रजपती के बातियों मैं मैं मैं मैं रजपती के बातियों मैं मैं राजपतियों मैं राजपती बातियों मैं राजपतियों मैं रजपतियों राजपतियों राजपतियों राजपतियों राजपतियों राजपतियों राजपतियों राजपतियों राजपतियों राजपतियों राजपतियों राजपतियों राजपतियों राजपतियों राजपतियों राजपतियों राजपतियों राजपतियों राजपतियों राजपतियों राजपतियों राजपतियों राजपतियों राजपतियों राजपतियों राजपतियों राजपतियों राजपतियों राजपतियों राजपतियों राजपतियों राजपतियं राजपतियों राजपतियों राजपतियों राजपतियों राजपतियों राजपतियों राजपतियों राजपतियों राजपतियों राजपतियों राजपतियों राजपतियों राजपतियों राजपतियों राजपतियों राजपतियों राजपतियों राजपतियों राजपतियों