[
{
"subject": "Rajasthan History",
"topic": "Mewar",
"question_en": "Who was the founder of the Mewar kingdom?",
"question_hi": "मेवाड़ राज्य के संस्थापक कौन थे?",
"A_en": "Bappa Rawal", "A_hi": "बप्पा रावल",
"B_en": "Rana Pratap", "B_hi": "राणा प्रताप",
"C_en": "Maharana Lakha", "C_hi": "महाराणा लाखा",
"D_en": "Kumbha", "D_hi": "कुंभा",
"answer": "A",
"explanation_en": "Bappa Rawal is considered the founder of the Mewar kingdom.",
"explanation_hi": "बप्पा रावल को मेवाड़ राज्य का संस्थापक माना जाता है।"
},
{
"subject": "Rajasthan History",
"topic": "Mewar",
"question_en": "Which Maharana of Mewar is famous for his bravery in the Battle of Haldighati?",
"question_hi": "मेवाड़ के किस महाराणा को हल्दीघाटी की लड़ाई में अपनी बहादुरी के लिए प्रसिद्ध है?",
"A_en": "Rana Pratap", "A_hi": "राणा प्रताप",
"B_en": "Rana Sanga", "B_hi": "राणा सांगा",
"C_en": "Maharana Kumbha", "C_hi": "महाराणा कुंभा",
"D_en": "Maharana Lakha", "D_hi": "महाराणा लाखा",
"answer": "A",
"explanation_en": "Rana Pratap is famous for his bravery in the Battle of Haldighati.",
"explanation_hi": "राणा प्रताप हल्दीघाटी की लड़ाई में अपनी बहादुरी के लिए प्रसिद्ध हैं।"
},
{
"subject": "Rajasthan History",
"topic": "Mewar",
"question_en": "What is the name of the famous fort in Udaipur, Mewar?",
"question_hi": "मेवाड़ के उदयपुर में स्थित प्रसिद्ध किले का क्या नाम है?",
"A_en": "City Palace", "A_hi": "सिटी पैलेस",
"B_en": "Lake Palace", "B_hi": "लेक पैलेस",
"C_en": "Jag Mandir", "C_hi": "जग मंदिर",
"D_en": "Monsoon Palace", "D_hi": "मॉनसून पैलेस",
"answer": "A",
"explanation_en": "The famous fort in Udaipur, Mewar is known as City Palace.",
"explanation_hi": "मेवाड़ के उदयपुर में स्थित प्रसिद्ध किला सिटी पैलेस है।"
},
{
"subject": "Rajasthan History",
"topic": "Mewar",
"question_en": "Which lake is situated in Udaipur, Mewar?",
"question_hi": "मेवाड़ के उदयपुर में कौन सी झील स्थित है?",
"A_en": "Lake Pichola", "A_hi": "पिचोला झील",
"B_en": "Lake Fateh Sagar", "B_hi": "फतेह सागर झील",
"C_en": "Lake Ranakpur", "C_hi": "राणकपुर झील",
"D_en": "Lake Pushkar", "D_hi": "पुष्कर झील",
"answer": "A",
"explanation_en": "Lake Pichola is situated in Udaipur, Mewar.",
"explanation_hi": "पिचोला झील मेवाड़ के उदयपुर में स्थित है।"
},
{
"subject": "Rajasthan History",
"topic": "Mewar",
"question_en": "Who was the queen of Maharana Pratap?",
"question_hi": "महाराणा प्रताप की रानी कौन थी?",
"A_en":": "Ajabde Bai", "A_hi": "अजबदे बाई",
"B_en": "Rani Jivanti", "B_hi": "रानी जीवंती",
"C_en": "Rani Roopmati", "C_hi": "रानी रूपमती",
"D_en": "Rani Phool Bai", "D_hi": "रानी फूल बाई",
"answer": "A",
"explanation_en": "Ajabde Bai was the queen of Maharana Pratap.",
"explanation_hi": "अजबदे बाई महाराणा प्रताप की रानी थी।"
},
{
"subject": "Rajasthan History",
"topic": "Mewar",
"question_en": "What was the name of the horse of Maharana Pratap?",
"question_hi": "महाराणा प्रताप का घोड़े का क्या नाम था?",
"A_en": "Chandra", "A_hi": "चंद्र",
"B_en": "Chaitanya", "B_hi": "चैतन्य",
"C_en": "Khamli", "C_hi": "खमली",
"D_en": "Chakravarti", "D_hi": "चक्रवर्ती",
"answer": "C",
"explanation_en": "The name of the horse of Maharana Pratap was Khamli.",
"explanation_hi": "महाराणा प्रताप के घोड़े का नाम खमली था।"
},
{
"subject": "Rajasthan History",
"topic": "Mewar",
"question_en": "Who built the Eklingji Temple in Mewar?",
"question_hi": "मेवाड़ में एकलिंगजी मंदिर का निर्माण किसने करवाया था?",
"A_en": "Rana Lakha", "A_hi": "राणा लाखा",
"B_en": "Rana Kumbha", "B_hi": "राणा कुंभा",
"C_en": "Rana Pratap", "C_hi": "राणा प्रताप",
"D_en": "Rana Sanga", "D_hi": "राणा सांगा",
"answer": "B",
"explanation_en": "Rana Kumbha built the Eklingji Temple in Mewar.",
"explanation_hi": "राणा कुंभा ने मेवाड़ में एकलिंगजी मंदिर का निर्माण करवाया था।"
},
{
"subject": "Rajasthan History",
"topic": "Mewar",
"question_en": "In which year did Maharana Pratap die?",
"question_hi": "महाराणा प्रताप की मृत्यु किस वर्ष में हुई थी?",
"A_en": "1596", "A_hi": "1596",
"B_en": "1597", "B_hi": "1597",
"C_en": "1598", "C_hi": "1598",
"D_en": "1599", "D_hi": "1599",
"answer": "B",
"explanation_en": "Maharana Pratap died in 1597.",
"explanation_hi": "महाराणा प्रताप की मृत्यु 1597 में हुई थी।"
},
{
"subject": "Rajasthan History",
"topic": "Mewar",
"question_en": "Who was the Diwan of Mewar during the reign of Maharana Pratap?",
"question_hi": "महाराणा प्रताप के शासनकाल में मेवाड़ का दीवान कौन था?",
"A_en": "Amar Singh", "A_hi": "अमर सिंह",
"B_en": "Raghuvanshi", "B_hi": "राघुवंशी",
"C_en": "Banwari", "C_hi": "बांवरी",
"D_en": "Chandrama", "D_hi": "चंद्रमा",
"answer": "C",
"explanation_en": "Banwari was the Diwan of Mewar during the reign of Maharana Pratap.",
"explanation_hi": "महाराणा प्रताप के शासनकाल में मेवाड़ का दीवान बांवरी था।"
},
{
"subject": "Rajasthan History",
"topic": "Mewar",
"question_en": "What was the name of the son of Maharana Pratap?",
"question_hi": "महाराणा प्रताप के पुत्र का क्या नाम था?",
"A_en": "Amar Singh", "A_hi": "अमर सिंह",
"B_en": "Rana Sanga", "B_hi": "राणा सांगा",
"C_en": "Raghuvanshi", "C_hi": "राघुवंशी",
"D_en": "Shankar", "D_hi": "शंकर",
"answer": "A",
"explanation_en": "The name of the son of Maharana Pratap was Amar Singh.",
"explanation_hi": "महाराणा प्रताप के पुत्र का नाम अमर सिंह था।"
}
]