[
{
"subject": "Rajasthan History",
"topic": "Mewar",
"question_en": "Who was the founder of the Mewar Kingdom?",
"question_hi": "मेवाड़ राज्य के संस्थापक कौन थे?",
"A_en": "Bappa Rawal", "A_hi": "बप्पा रावल",
"B_en": "Rana Pratap", "B_hi": "राणा प्रताप",
"C_en": "Rawal Jaisal", "C_hi": "रावल जैसल",
"D_en": "Prithviraj Chauhan", "D_hi": "पृथ्वीराज चौहान",
"answer": "A",
"explanation_en": "Bappa Rawal is considered the founder of the Mewar Kingdom.",
"explanation_hi": "बप्पा रावल को मेवाड़ राज्य का संस्थापक माना जाता है।"
},
{
"subject": "Rajasthan History",
"topic": "Mewar",
"question_en": "Which Rana of Mewar is famous for his bravery in the Battle of Haldighati?",
"question_hi": "मेवाड़ के किस राणा को हल्दीघाटी की लड़ाई में अपनी बहादुरी के लिए प्रसिद्ध है?",
"A_en": "Rana Sanga", "A_hi": "राणा सांगा",
"B_en": "Rana Pratap", "B_hi": "राणा प्रताप",
"C_en": "Rana Udai Singh", "C_hi": "राणा उदय सिंह",
"D_en": "Rana Lakha", "D_hi": "राणा लाखा",
"answer": "B",
"explanation_en": "Rana Pratap is famous for his bravery in the Battle of Haldighati.",
"explanation_hi": "राणा प्रताप हल्दीघाटी की लड़ाई में अपनी बहादुरी के लिए प्रसिद्ध है।"
},
{
"subject": "Rajasthan History",
"topic": "Mewar",
"question_en": "What was the name of the queen of Rana Pratap, who accompanied him in the Battle of Haldighati?",
"question_hi": "रणा प्रताप की पत्नी का क्या नाम था, जो हल्दीघाटी की लड़ाई में उनके साथ थीं?",
"A_en":": "Rani Jivanti", "A_hi": "रानी जीवंती",
"B_en": "Rani Phool Bai", "B_hi": "रानी फूल बाई",
"C_en": "Rani Udantabai", "C_hi": "रानी उदंतबाई",
"D_en": "Rani Ajabde", "D_hi": "रानी अजबदे",
"answer": "D",
"explanation_en": "Rani Ajabde was the queen of Rana Pratap, who accompanied him in the Battle of Haldighati.",
"explanation_hi": "रानी अजबदे रणाप्रताप की पत्नी थी, जो हल्दीघाटी की लड़ाई में उनके साथ थी।"
},
{
"subject": "Rajasthan History",
"topic": "Mewar",
"question_en": "Which Mughal emperor invaded Mewar and forced Rana Udai Singh to leave Chittor?",
"question_hi": "किस मुगल बादशाह ने मेवाड़ पर आक्रमण किया और राणा उदय सिंह को चित्तौड़ छोड़ने के लिए मजबूर किया?",
"A_en": "Akbar", "A_hi": "अकबर",
"B_en": "Jahangir", "B_hi": "जहांगीर",
"C_en": "Shah Jahan", "C_hi": "शाहजहां",
"D_en": "Aurangzeb", "D_hi": "औरंगजेब",
"answer": "A",
"explanation_en": "Akbar invaded Mewar and forced Rana Udai Singh to leave Chittor.",
"explanation_hi": "अकबर ने मेवाड़ पर आक्रमण किया और राणा उदय सिंह को चित्तौड़ छोड़ने के लिए मजबूर किया।"
},
{
"subject": "Rajasthan History",
"topic": "Mewar",
"question_en": "What was the name of the famous fort built by Rana Kumbha in the 15th century?",
"question_hi": "15वीं शताब्दी में राणा कुंभा द्वारा बनवाया गया प्रसिद्ध किला क्या था?",
"A_en": "Kumbhalgarh Fort", "A_hi": "कुंभलगढ़ किला",
"B_en": "Rana Pratap Sagar Dam", "B_hi": "राणा प्रताप सागर बांध",
"C_en": "City Palace", "C_hi": "सिटी पैलेस",
"D_en": "Jagdish Temple", "D_hi": "जगदीश मंदिर",
"answer": "A",
"explanation_en": "The famous fort built by Rana Kumbha in the 15th century was Kumbhalgarh Fort.",
"explanation_hi": "15वीं शताब्दी में राणा कुंभा द्वारा बनवाया गया प्रसिद्ध किला कुंभलगढ़ किला था।"
},
{
"subject": "Rajasthan History",
"topic": "Mewar",
"question_en": "Who was the famous poet and scholar of Mewar during the reign of Rana Kumbha?",
"question_hi": "राणा कुंभा के शासनकाल के दौरान मेवाड़ के प्रसिद्ध कवि और विद्वान कौन थे?",
"A_en": "Kaviraj Madhav", "A_hi": "कविराज माधव",
"B_en": "Raghunatha Rabari", "B_hi": "रघुनाथ राबरी",
"C_en": "Amir Khusrau", "C_hi": "अमीर खुसरो",
"D_en": "Vidyaranya", "D_hi": "विद्यारण्य",
"answer": "D",
"explanation_en": "Vidyaranya was the famous poet and scholar of Mewar during the reign of Rana Kumbha.",
"explanation_hi": "विद्यारण्य राणा कुंभा के शासनकाल के दौरान मेवाड़ के प्रसिद्ध कवि और विद्वान थे।"
},
{
"subject": "Rajasthan History",
"topic": "Mewar",
"question_en": "Which Mughal emperor granted a portion of Mewar to Maharana Pratap's son, Amar Singh?",
"question_hi": "किस मुगल बादशाह ने महाराणा प्रताप के पुत्र अमर सिंह को मेवाड़ का एक हिस्सा दिया?",
"A_en": "Akbar", "A_hi": "अकबर",
"B_en": "Jahangir", "B_hi": "जहांगीर",
"C_en": "Shah Jahan", "C_hi": "शाहजहां",
"D_en": "Aurangzeb", "D_hi": "औरंगजेब",
"answer": "B",
"explanation_en": "Jahangir granted a portion of Mewar to Maharana Pratap's son, Amar Singh.",
"explanation_hi": "जहांगीर ने महाराणा प्रताप के पुत्र अमर सिंह को मेवाड़ का एक हिस्सा दिया।"
},
{
"subject": "Rajasthan History",
"topic": "Mewar",
"question_en": "What was the name of the famous lake in Udaipur, built by Maharana Lakha in the 14th century?",
"question_hi": "उदयपुर में 14वीं शताब्दी में महाराणा लाखा द्वारा बनवाई गई प्रसिद्ध झील का क्या नाम था?",
"A_en": "Lake Pichola", "A_hi": "पिचोला झील",
"B_en": "Lake Fateh Sagar", "B_hi": "फतेह सागर झील",
"C_en": "Lake Udai Sagar", "C_hi": "उदय सागर झील",
"D_en": "Lake Nagda", "D_hi": "नागड़ा झील",
"answer": "A",
"explanation_en": "The famous lake in Udaipur, built by Maharana Lakha in the 14th century, was Lake Pichola.",
"explanation_hi": "उदयपुर में 14वीं शताब्दी में महाराणा लाखा द्वारा बनवाई गई प्रसिद्ध झील पिचोला झील थी।"
},
{
"subject": "Rajasthan History",
"topic": "Mewar",
"question_en": "Who was the ruler of Mewar during the reign of Mughal emperor Aurangzeb?",
"question_hi": "मुगल बादशाह औरंगजेब के शासनकाल के दौरान मेवाड़ के शासक कौन थे?",
"A_en": "Rana Pratap", "A_hi": "राणा प्रताप",
"B_en": "Rana Amar Singh", "B_hi": "राणा अमर सिंह",
"C_en": "Rana Raj Singh", "C_hi": "राणा राज सिंह",
"D_en": "Rana Sahib Singh", "D_hi": "राणा साहिब सिंह",
"answer": "C",
"explanation_en": "Rana Raj Singh was the ruler of Mewar during the reign of Mughal emperor Aurangzeb.",
"explanation_hi": "मुगल बादशाह औरंगजेब के शासनकाल के दौरान मेवाड़ के शासक राणा राज सिंह थे।"
},
{
"subject": "Rajasthan History",
"topic": "Mewar",
"question_en": "What was the name of the famous palace built in Udaipur during the reign of Maharana Jagat Singh?",
"question_hi": "महाराणा जगत सिंह के शासनकाल के दौरान उदयपुर में बनवाया गया प्रसिद्ध महल क्या था?",
"A_en": "Jagdish Temple", "A_hi": "जगदीश मंदिर",
"B_en": "City Palace", "B_hi": "सिटी पैलेस",
"C_en": "Monsoon Palace", "C_hi": "मौसमी महल",
"D_en": "Kumbhalgarh Fort", "D_hi": "कुंभलगढ़ किला",
"answer": "A",
"explanation_en": "The famous palace built in Udaipur during the reign of Maharana Jagat Singh was Jagdish Temple.",
"explanation_hi": "महाराणा जगत सिंह के शासनकाल के दौरान उदयपुर में बनवाया गया प्रसिद्ध महल जगदीश मंदिर था।"
}
]