[
{
"subject": "Rajasthan History",
"topic": "Mewar",
"question_en": "Who was the founder of the Mewar Kingdom?",
"question_hi": "मेवाड़ राज्य के संस्थापक कौन थे?",
"A_en": "Bappa Rawal", "A_hi": "बप्पा रावल",
"B_en": "Rana Pratap", "B_hi": "राणा प्रताप",
"C_en": "Rawal Jaisal", "C_hi": "रावल जैसल",
"D_en": "Kumbha", "D_hi": "कुंभा",
"answer": "A",
"explanation_en": "Bappa Rawal is considered the founder of the Mewar Kingdom.",
"explanation_hi": "बप्पा रावल को मेवाड़ राज्य का संस्थापक माना जाता है।"
},
{
"subject": "Rajasthan History",
"topic": "Mewar",
"question_en": "What is the other name of Rana Pratap Sagar Dam?",
"question_hi": "राणा प्रताप सागर बांध का अन्य नाम क्या है?",
"A_en": "Pong Dam", "A_hi": "पोंग बांध",
"B_en": "Ranakpur Dam", "B_hi": "राणकपुर बांध",
"C_en": "Mahi Bajaj Sagar Dam", "C_hi": "माही बाजाज सागर बांध",
"D_en": "Priti Sagar", "D_hi": "प्रीति सागर",
"answer": "D",
"explanation_en": "Rana Pratap Sagar Dam is also known as Priti Sagar or Rana Pratap Sagar.",
"explanation_hi": "राणा प्रताप सागर बांध को प्रीति सागर या राणा प्रताप सागर के नाम से भी जाना जाता है।"
},
{
"subject": "Rajasthan History",
"topic": "Mewar",
"question_en": "In which year did Rana Pratap take oath of freedom?",
"question_hi": "राणा प्रताप ने स्वतंत्रता की शपथ किस वर्ष ली थी?",
"A_en": "1576", "A_hi": "1576",
"B_en": "1597", "B_hi": "1597",
"C_en": "1596", "C_hi": "1596",
"D_en": "1650", "D_hi": "1650",
"answer": "C",
"explanation_en": "Rana Pratap took oath of freedom in 1596 at Kumbhalgarh.",
"explanation_hi": "राणा प्रताप ने 1596 में कुंभलगढ़ में स्वतंत्रता की शपथ ली थी।"
},
{
"subject": "Rajasthan History",
"topic": "Mewar",
"question_en": "Who built the famous Ranakpur Jain temple?",
"question_hi": "प्रसिद्ध राणकपुर जैन मंदिर का निर्माण किसने करवाया था?",
"A_en": "Dhariksha Shah", "A_hi": "धरिक्ष शाह",
"B_en": "Kumbha", "B_hi": "कुंभा",
"C_en": "Rana Pratap", "C_hi": "राणा प्रताप",
"D_en": "Sardar Pal", "D_hi": "सरदार पाल",
"answer": "B",
"explanation_en": "The famous Ranakpur Jain temple was built by Kumbha in 1439.",
"explanation_hi": "प्रसिद्ध राणकपुर जैन मंदिर का निर्माण 1439 में कुंभा ने करवाया था।"
},
{
"subject": "Rajasthan History",
"topic": "Mewar",
"question_en": "What was the original name of Udaipur city?",
"question_hi": "उदयपुर शहर का मूल नाम क्या था?",
"A_en": "Ujjain", "A_hi": "उज्जैन",
"B_en": "Mewar", "B_hi": "मेवाड़",
"C_en": "Kumbhalgarh", "C_hi": "कुंभलगढ़",
"D_en": "Nagda", "D_hi":","नागदा",
"answer": "D",
"explanation_en": "The original name of Udaipur city was Nagda.",
"explanation_hi": "उदयपुर शहर का मूल नाम नागदा था।"
},
{
"subject": "Rajasthan History",
"topic": "Mewar",
"question_en": "Who was the queen of Maharana Pratap?",
"question_hi": "महाराणा प्रताप की रानी कौन थी?",
"A_en":": "Ajabde Bai", "A_hi": "अजबदे बाई",
"B_en": "Rani Laxmibai", "B_hi": "रानी लक्ष्मीबाई",
"C_en": "Jivanti Bai", "C_hi": "जीवंती बाई",
"D_en": "Phul Bai", "D_hi": "फूल बाई",
"answer": "A",
"explanation_en": "The queen of Maharana Pratap was Ajabde Bai.",
"explanation_hi": "महाराणा प्रताप की रानी अजबदे बाई थी।"
},
{
"subject": "Rajasthan History",
"topic": "Mewar",
"question_en": "Who built the City Palace in Udaipur?",
"question_hi": "उदयपुर में सिटी पैलेस का निर्माण किसने करवाया?",
"A_en": "Maharana Lakha", "A_hi": "महाराणा लाखा",
"B_en": "Maharana Pratap", "B_hi": "महाराणा प्रताप",
"C_en": "Maharana Udai Singh", "C_hi": "महाराणा उदय सिंह",
"D_en": "Sawai Jai Singh", "D_hi": "सवाई जय सिंह",
"answer": "C",
"explanation_en": "The City Palace in Udaipur was built by Maharana Udai Singh in 1572.",
"explanation_hi": "उदयपुर में सिटी पैलेस का निर्माण 1572 में महाराणा उदय सिंह ने करवाया था।"
},
{
"subject": "Rajasthan History",
"topic": "Mewar",
"question_en": "What is the name of Rana Pratap's horse?",
"question_hi": "राणा प्रताप के घोड़े का नाम क्या था?",
"A_en": "Chaitanya", "A_hi": "चैतन्य",
"B_en": "Pratap", "B_hi": "प्रताप",
"C_en": "Champi", "C_hi": "चांपि",
"D_en": "Chhodagarh", "D_hi": "छोडagar",
"answer": "C",
"explanation_en": "The name of Rana Pratap's horse was Champi.",
"explanation_hi": "राणा प्रताप के घोड़े का नाम चांपि था।"
},
{
"subject": "Rajasthan History",
"topic": "Mewar",
"question_en": "Who was the ruler of Mewar during the reign of Akbar?",
"question_hi": "अकबर के शासनकाल में मेवाड़ का शासक कौन था?",
"A_en": "Rana Pratap", "A_hi": "राणा प्रताप",
"B_en": "Rana Udai Singh", "B_hi": "राणा उदय सिंह",
"C_en": "Rana Kumbha", "C_hi": "राणा कुंभा",
"D_en": "Rana Raimal", "D_hi": "राणा राइमल",
"answer": "B",
"explanation_en": "Rana Udai Singh was the ruler of Mewar during the reign of Akbar.",
"explanation_hi": "अकबर के शासनकाल में मेवाड़ का शासक राणा उदय सिंह था।"
},
{
"subject": "Rajasthan History",
"topic": "Mewar",
"question_en": "In which battle did Maharana Pratap fight against Mughal Emperor Akbar?",
"question_hi": "किस युद्ध में महाराणा प्रताप ने मुगल सम्राट अकबर के खिलाफ लड़ाई लड़ी?",
"A_en": "Battle of Khanua", "A_hi": "खानुआ की लड़ाई",
"B_en": "Battle of Tarakanth", "B_hi": "तराकंठ की लड़ाई",
"C_en": "Battle of Haldighati", "C_hi": "हल्दीघाटी की लड़ाई",
"D_en": "Battle of Gogaunda", "D_hi": "गोगुंदा की लड़ाई",
"answer": "C",
"explanation_en": "The famous Battle of Haldighati took place in 1576 between Maharana Pratap and Mughal Emperor Akbar.",
"explanation_hi": "प्रसिद्ध हल्दीघाटी की लड़ाई 1576 में महाराणा प्रताप और मुगल सम्राट अकबर के बीच हुई थी।"
}
]