[
{
"subject": "General Science",
"topic": "Vidyut Dhara, Ohm ka Niyam aur Electric Motor",
"question_en": "What is the formula for Ohm's Law?",
"question_hi": "ओम का नियम क्या है।",
"A_en": "V = IR",
"A_hi": "V = I × R",
"B_en": "V = W/T",
"B_hi": "V = W/T",
"C_en": "R = V/I",
"C_hi": "R = V/I",
"D_en": "E = I × R × T",
"D_hi": "E = I × R × T",
"answer": "D",
"explanation_en": "Ohm's Law states that the electric potential difference (voltage) V is equal to the product of electric current I and resistance R.\nOhm's Law formula is: V = I × R.",
"explanation_hi": "ओम का नियम है कि पूर्वानुभवन (विद्यार्थ संदेश: V = I × R.",
},
{
"subject": "General Science",
"topic": "Vidyut Dhara, Ohm ka Niyam aur Electric Motor",
"question_en": "What is the formula for calculating the resistance of a conductor?",
"question_hi": "अध्यायक के इस्यावर्ण (आवर्ण के इस्यावर्ण (आवर्ण के इस्यावर्ण (आवर्ण के इस्यावर्ण (आवर्ण के इस्यावर्ण (आवर्ण के इस्यावर्ण (आवर्ण के इस्यावर्ण (आवर्ण के इस्यावर्ण (आवर्ण के इस्यावर्ण (आवर्ण के इस्यावर्ण (आवर्ण के इस्यावर्ण (आवर्ण के इस्यावर्ण (आवर्ण के इस्यावर्ण (आवर्ण के इस्यावर्ण (आवर्ण के इस्यावर्ण (आवर्ण के इस्यावर्ण (आवर्ण के इस्यावर्ण (आवर्ण के इस्यावर्ण (आवर्ร के इस्यावर्ण (आवर्ร के इस्यावर्ण (आवर्ण के इस्यावर्ण (आवर्ร के इस्यावर्ण (आवर्ण के इस्यावर्ण (आवर्ण के इस्यावर्ण (आवर्ร के इस्यावर्ण (आवर्ร के इस्यावर्ण (आवर्ण के इस्यावर्ण (आवर्ण के इस्यावर्ण (आवर्ण के इस्यावर्ण (आवर्ण के इस्यावर्ण (आवर्ण के इस्यावर्ण (आवर्ण के इस्यावर्ण (आवर्ण के इस्यावर्ण (आवर्ण के इस्यावर्ण (आवर्ण के इस्यावर्ण (आवर्ण के इस्यावर्ण (आवर्ण के इस्यावर्ण (आवर्ण के इस्यावर्ण (आवर्ण के इस्यावर्ण (आवर्ण के इस्यावर्ण (आवर्ण)",
Sir, इस्यावर्ण (आवर्ण)",

"question_en": "What is the formula for calculating the resistance of a wire?",
"question_hi": "क्ण (इस्यावर्ण)",
"A_en": "National conductance (इस्यावर्ण)",
"A_hi": "इस्ण (इस्ण)",
"B_en": "Moh (इस्ण)",
"B_hi": "इस्ण (इस्ण)",
"C_en": "Resistance (इस्ण)",
"C_hi": "इस्ण (इस्ण)",
"D_en": "Electric resistance (इस्ण)",
"D_hi": "इस्ण (इस्ण)",
"answer": "D",
"explanation_en": "The formula for calculating the resistance of a wire is R = 1/(D)",
"explanation_hi": "इस्ण (इस्ण)",
"explanation_en": "The formula for calculating the resistance of a wire is R = \(1/D\)",
"explanation_hi": "इस्ण (इस्ण (इस्ण)",
"answer": "D",
"question_en": "What is the formula for calculating the resistance of a wire?",
"question_hi": "इस्ण (इस्ण)",
"A_en": "Resistivity",
"A_hi": "इस्ण (इस्ण)",
"B_en": "Resistance",
"B_hi": "इस्ण (इस्ण)",
"C_en": "Resistivity",
"C_hi": "इस्ण (इस्ण)",
"D_en": "Resistivity",
"D_hi": "इस्ण (इस्ण)",
"answer": "D",
"explanation_en": "The formula for calculating the resistance of a wire is R = \(1/D\",
"explanation_hi": "इस्ण (इस्ण)",
]
]