[
{
"subject": "Rajasthan Geography",
"topic": "Rajasthan ki Pramukh Jheelen: Namkeen aur Meethi Jheelen",
"question_en": "Which is the largest saline (namkeen) lake in Rajasthan?",
"question_hi": "राजस्थान की सबसे बड़ी नमकीन झील कौन सी है?",
"A_en": "Sambhar Lake", "A_hi": "सांभर झील",
"B_en": "Pushkar Lake", "B_hi": "पुष्कर झील",
"C_en": "Nakki Lake", "C_hi": "नक्की झील",
"D_en": "Badi Lake", "D_hi": "बड़ी झील",
"answer": "A",
"explanation_en": "Sambhar Lake, covering about 230 sq km, is the largest saline lake in Rajasthan.",
"explanation_hi": "सांभर झील, लगभग 230 वर्ग किमी क्षेत्रफल के साथ, राजस्थान की सबसे बड़ी नमकीन झील है।"
},
{
"subject": "Rajasthan Geography",
"topic": "Rajasthan ki Pramukh Jheelen: Namkeen aur Meethi Jheelen",
"question_en": "Pushkar Lake, situated near Ajmer, is classified as a:",
"question_hi": "अजमेर के पास स्थित पुष्कर झील किस प्रकार की झील है?",
"A_en": "Saline lake", "A_hi": "नमकीन झील",
"B_en": "Sweet (fresh) lake", "B_hi": "मीठी (ताज़ा) झील",
"C_en": "Artificial reservoir", "C_hi": "कृत्रिम जलाशय",
"D_en": "Seasonal pond", "D_hi": "मौसमी तालाब",
"answer": "B",
"explanation_en": "Pushkar Lake is a perennial freshwater lake used for religious rituals.",
"explanation_hi": "पुष्कर झील एक स्थायी मीठी झील है जो धार्मिक अनुष्ठानों में उपयोग होती है।"
},
{
"subject": "Rajasthan Geography",
"topic": "Rajasthan ki Pramukh Jheelen: Namkeen aur Meethi Jheelen",
"question_en": "Which saline lake lies in the Nagaur district and is known for its high salt content?",
"question_hi": "नागर जिले में स्थित कौन सी नमकीन झील अपने उच्च नमक स्तर के लिए जानी जाती है?",
"A_en": "Didwana Lake", "A_hi": "दिड़वाना झील",
"B_en": "Nakki Lake", "B_hi": "नक्की झील",
"C_en": "Sajjangarh Lake", "C_hi": "सज्जनगढ़ झील",
"D_en": "Fateh Sagar Lake", "D_hi": "फ़तेह सागर झील",
"answer": "A",
"explanation_en": "Didwana Lake in Nagaur district is a typical saline lake with extensive salt pans around it.",
"explanation_hi": "नागर जिले में स्थित दिड़वाना झील एक विशेष नमकीन झील है, जिसके आसपास बड़े नमक के पैन हैं।"
},
{
"subject": "Rajasthan Geography",
"topic": "Rajasthan ki Pramukh Jheelen: Namkeen aur Meethi Jheelen",
"question_en": "Nakki Lake, a sweet water lake, is located near which hill station?",
"question_hi": "नक्की झील, एक मीठी जल झील, किस हिल स्टेशन के निकट स्थित है?",
"A_en": "Mount Abu", "A_hi": "माउंट आबू",
"B_en": "Udaipur", "B_hi": "उदयपुर",
"C_en": "Jaisalmer", "C_hi": "जैसलमेर",
"D_en": "Bikaner", "D_hi": "बीकानेर",
"answer": "A",
"explanation_en": "Nakki Lake is situated at Mount Abu, the only hill station of Rajasthan.",
"explanation_hi": "नक्की झील माउंट आबू में स्थित है, जो राजस्थान का एकमात्र हिल स्टेशन है।"
},
{
"subject": "Rajasthan Geography",
"topic": "Rajasthan ki Pramukh Jheelen: Namkeen aur Meethi Jheelen",
"question_en": "Which of the following lakes is primarily used for commercial salt extraction?",
"question_hi": "निम्नलिखित में से कौन सी झील मुख्यतः वाणिज्यिक नमक निष्कर्षण के लिए उपयोग की जाती है?",
"A_en": "Sambhar Lake", "A_hi": "सांभर झील",
"B_en": "Pushkar Lake", "B_hi": "पुष्कर झील",
"C_en": "Fateh Sagar Lake", "C_hi": "फ़तेह सागर झील",
"D_en": "Badi Lake", "D_hi": "बड़ी झील",
"answer": "A",
"explanation_en": "Sambhar Lake hosts extensive salt pans and is the major source of salt in India.",
"explanation_hi": "सांभर झील में बड़े नमक पैन हैं और यह भारत में नमक का प्रमुख स्रोत है।"
},
{
"subject": "Rajasthan Geography",
"topic": "Rajasthan ki Pramukh Jheelen: Namkeen aur Meethi Jheelen",
"question_en": "The lake known as 'Moti Jheel' in Bikaner district is:",
"question_hi": "बीकानेर जिले में 'मोती झील' के नाम से जानी जाने वाली झील किस प्रकार की है?",
"A_en": "A sweet water lake", "A_hi": "मीठी जल झील",
"B_en": "A saline lake", "B_hi": "नमकीन झील",
"C_en": "A man‑made reservoir", "C_hi": "कृत्रिम जलाशय",
"D_en": "A seasonal pond", "D_hi": "मौसमी तालाब",
"answer": "B",
"explanation_en": "Moti Jheel is a saline lake situated in the arid region of Bikaner.",
"explanation_hi": "मोती झील बीकानेर के शुष्क क्षेत्र में स्थित एक नमकीन झील है।"
},
{
"subject": "Rajasthan Geography",
"topic": "Rajasthan ki Pramukh Jheelen: Namkeen aur Meethi Jheelen",
"question_en": "Which sweet lake in Rajasthan is famous for its lotus flowers and a floating market?",
"question_hi": "राजस्थान की कौन सी मीठी झील अपने कमल के फूलों और तैरते बाजार के लिए प्रसिद्ध है?",
"A_en": "Pushkar Lake", "A_hi": "पुष्कर झील",
"B_en": "Nakki Lake", "B_hi": "नक्की झील",
"C_en": "Pichola Lake", "C_hi": "पिचोला झील",
"D_en": "Sambhar Lake", "D_hi": "सांभर झील",
"answer": "C",
"explanation_en": "Pichola Lake in Udaipur is renowned for its lotus blossoms and the occasional floating market.",
"explanation_hi": "उदयपुर की पिचोला झील अपने कमल के फूलों और कभी‑कभी होने वाले तैरते बाजार के लिए प्रसिद्ध है।"
},
{
"subject": "Rajasthan Geography",
"topic": "Rajasthan ki Pramukh Jheelen: Namkeen aur Meethi Jheelen",
"question_en": "The lake 'Badi' situated near Jodhpur is classified as:",
"question_hi": "जोधपुर के पास स्थित 'बड़ी' झील को किस श्रेणी में रखा जाता है?",
"A_en": "Saline lake", "A_hi": "नमकीन झील",
"B_en": "Sweet lake", "B_hi": "मीठी झील",
"C_en": "Artificial dam", "C_hi": "कृत्रिम बांध",
"D_en": "Rain‑fed pond", "D_hi": "वर्षा‑संचित तालाब",
"answer": "A",
"explanation_en": "Badi Lake is a seasonal saline lake that often dries up during summer.",
"explanation_hi": "बड़ी झील एक मौसमी नमकीन झील है, जो अक्सर गर्मियों में सूख जाती है।"
},
{
"subject": "Rajasthan Geography",
"topic": "Rajasthan ki Pramukh Jheelen: Namkeen aur Meethi Jheelen",
"question_en": "Which lake serves as a major source of drinking water for the city of Udaipur?",
"question_hi": "उदयपुर शहर के लिए कौन सी झील प्रमुख पेयजल स्रोत है?",
"A_en": "Fateh Sagar Lake", "A_hi": "फ़तेह सागर झील",
"B_en": "Sambhar Lake", "B_hi": "सांभर झील",
"C_en": "Didwana Lake", "C_hi": "दिड़वाना झील",
"D_en": "Moti Jheel", "D_hi": "मोती झील",
"answer": "A",
"explanation_en": "Fateh Sagar Lake, created by a dam on the Banas River, supplies most of Udaipur's drinking water.",
"explanation_hi": "बनास नदी पर बांध द्वारा निर्मित फ़तेह सागर झील उदयपुर के अधिकांश पेयजल की आपूर्ति करती है।"
},
{
"subject": "Rajasthan Geography",
"topic": "Rajasthan ki Pramukh Jheelen: Namkeen aur Meethi Jheelen",
"question_en": "The term 'Namkeen Jheel' primarily refers to lakes that:",
"question_hi": "'नमकीन झील' शब्द मुख्यतः उन झीलों को दर्शाता है जो:",
"A_en": "contain high concentrations of dissolved salts", "A_hi": "घुले हुए नमक की उच्च मात्रा रखती हैं",
"B_en": "are used for irrigation", "B_hi": "सिचाई के लिये उपयोग की जाती हैं",
"C_en": "have abundant fish species", "C_hi": "समृद्ध मछली प्रजातियों से भरपूर हैं",
"D_en": "are formed by glacial activity", "D_hi": "हिमनदीय गतिविधियों से बनती हैं",
"answer": "A",
"explanation_en": "Namkeen lakes have high salinity due to evaporation exceeding inflow, leaving salts behind.",
"explanation_hi": "नमकीन झीलों में वाष्पीकरण इनफ़्लो से अधिक होने के कारण उच्च लवणता रहती है, जिससे नमक पीछे रह जाता है।"
}
]