[
{
"subject": "Rajasthan Geography",
"topic": "Thar Marusthal: Visheshatayen aur Vikas",
"question_en": "What is the approximate area of the Thar Desert in Rajasthan?",
"question_hi": "राजस्थान में थार मरुस्थल का अनुमानित क्षेत्रफल क्या है?",
"A_en": "1,20,000 sq km", "A_hi": "1,20,000 वर्ग किमी",
"B_en": "1,10,000 sq km", "B_hi": "1,10,000 वर्ग किमी",
"C_en": "1,30,000 sq km", "C_hi": "1,30,000 वर्ग किमी",
"D_en": "1,19,900 sq km", "D_hi": "1,19,900 वर्ग किमी",
"answer": "D",
"explanation_en": "The Thar Desert covers an area of approximately 1,19,900 sq km in Rajasthan.",
"explanation_hi": "थार मरुस्थल राजस्थान में लगभग 1,19,900 वर्ग किमी क्षेत्र में फैला हुआ है।"
},
{
"subject": "Rajasthan Geography",
"topic": "Thar Marusthal: Visheshatayen aur Vikas",
"question_en": "Which of the following rivers does not flow through the Thar Desert in Rajasthan?",
"question_hi": "निम्नलिखित में से कौन सी नदी राजस्थान के थार मरुस्थल से नहीं गुजरती है?",
"A_en": "Luni River", "A_hi": "लूनी नदी",
"B_en": "Banas River", "B_hi": "बाणास नदी",
"C_en": "Chambal River", "C_hi": "चंबल नदी",
"D_en": "Brahmani River", "D_hi": "ब्राह्मणी नदी",
"answer": "C",
"explanation_en": "The Chambal River does not flow through the Thar Desert in Rajasthan.",
"explanation_hi": "चंबल नदी राजस्थान के थार मरुस्थल से नहीं गुजरती है।"
},
{
"subject": "Rajasthan Geography",
"topic": "Thar Marusthal: Visheshatayen aur Vikas",
"question_en": "What is the main crop grown in the Thar Desert region of Rajasthan?",
"question_hi": "राजस्थान के थार मरुस्थल क्षेत्र में मुख्य रूप से कौन सी फसल उगाई जाती है?",
"A_en": "Wheat", "A_hi": "गेहूं",
"B_en": "Cotton", "B_hi": "कपास",
"C_en": "Bajra", "C_hi": "बाजरा",
"D_en": "Tobacco", "D_hi": "तम्बाकू",
"answer": "C",
"explanation_en": "Bajra is the main crop grown in the Thar Desert region of Rajasthan.",
"explanation_hi": "बाजरा राजस्थान के थार मरुस्थल क्षेत्र में मुख्य रूप से उगाई जाने वाली फसल है।"
},
{
"subject": "Rajasthan Geography",
"topic": "Thar Marusthal: Visheshatayen aur Vikas",
"question_en": "Which city in Rajasthan is known as the 'City of Palaces' and is not located in the Thar Desert?",
"question_hi": "राजस्थान में कौन सा शहर 'महलों का शहर' के नाम से जाना जाता है और थार मरुस्थल में स्थित नहीं है?",
"A_en": "Jaipur", "A_hi": "जयपुर",
"B_en": "Jodhpur", "B_hi": "जोधपुर",
"C_en": "Udaipur", "C_hi": "उदयपुर",
"D_en": "Ajmer", "D_hi": "अजमेर",
"answer": "A",
"explanation_en": "Jaipur is known as the 'City of Palaces' and is not located in the Thar Desert.",
"explanation_hi": "जयपुर 'महलों का शहर' के नाम से जाना जाता है और थार मरुस्थल में स्थित नहीं है।"
},
{
"subject": "Rajasthan Geography",
"topic": "Thar Marusthal: Visheshatayen aur Vikas",
"question_en": "What is the name of the canal that supplies water to the Thar Desert region of Rajasthan?",
"question_hi": "राजस्थान के थार मरुस्थल क्षेत्र को पानी की आपूर्ति करने वाली नहर का नाम क्या है?",
"A_en": "Indira Gandhi Canal", "A_hi": "इन्दिरा गांधी नहर",
"B_en": "Rajasthan Canal", "B_hi": "राजस्थान नहर",
"C_en": "Thar Canal", "C_hi": "थार नहर",
"D_en": "Luni Canal", "D_hi": "लूनी नहर",
"answer": "A",
"explanation_en": "The Indira Gandhi Canal supplies water to the Thar Desert region of Rajasthan.",
"explanation_hi": "इन्दिरा गांधी नहर राजस्थान के थार मरुस्थल क्षेत्र को पानी की आपूर्ति करती है।"
},
{
"subject": "Rajasthan Geography",
"topic": "Thar Marusthal: Visheshatayen aur Vikas",
"question_en": "Which of the following districts in Rajasthan is not located in the Thar Desert?",
"question_hi": "राजस्थान में निम्नलिखित में से कौन सा जिला थार मरुस्थल में स्थित नहीं है?",
"A_en": "Jodhpur", "A_hi": "जोधपुर",
"B_en": "Bikaner", "B_hi": "बीकानेर",
"C_en": "Udaipur", "C_hi": "उदयपुर",
"D_en": "Jaipur", "D_hi": "जयपुर",
"answer": "C",
"explanation_en": "Udaipur district is not located in the Thar Desert.",
"explanation_hi": "उदयपुर जिला थार मरुस्थल में स्थित नहीं है।"
},
{
"subject": "Rajasthan Geography",
"topic": "Thar Marusthal: Visheshatayen aur Vikas",
"question_en": "What is the name of the sand dunes found in the Thar Desert of Rajasthan?",
"question_hi": "राजस्थान के थार मरुस्थल में पाए जाने वाले रेत के टीलों का नाम क्या है?",
"A_en": "Eolian dunes", "A_hi": "एओलियन टीलें",
"B_en": "Longitudinal dunes", "B_hi": "अनुदैर्ध्य टीलें",
"C_en": "Transverse dunes", "C_hi": "अनुप्रस्थ टीलें",
"D_en": "Barchans", "D_hi":": "बर्कन",
"answer": "D",
"explanation_en": "The sand dunes found in the Thar Desert of Rajasthan are called Barchans.",
"explanation_hi": "राजस्थान के थार मरुस्थल में पाए जाने वाले रेत के टीलों को बर्कन कहा जाता है।"
},
{
"subject": "Rajasthan Geography",
"topic": "Thar Marusthal: Visheshatayen aur Vikas",
"question_en": "Which of the following is a major problem faced by the people living in the Thar Desert region of Rajasthan?",
"question_hi": "राजस्थान के थार मरुस्थल क्षेत्र में रहने वाले लोगों को निम्नलिखित में से कौन सी एक बड़ी समस्या का सामना करना पड़ता है?",
"A_en": "Water scarcity", "A_hi": "जल की कमी",
"B_en": "Soil erosion", "B_hi": "मिट्टी का क्षरण",
"C_en": "High temperature", "C_hi": "उच्च तापमान",
"D_en": "All of the above", "D_hi": "उपरोक्त सभी",
"answer": "D",
"explanation_en": "The people living in the Thar Desert region of Rajasthan face problems like water scarcity, soil erosion, and high temperature.",
"explanation_hi": "राजस्थान के थार मरुस्थल क्षेत्र में रहने वाले लोगों को जल की कमी, मिट्टी का क्षरण, और उच्च तापमान जैसी समस्याओं का सामना करना पड़ता है।"
},
{
"subject": "Rajasthan Geography",
"topic": "Thar Marusthal: Visheshatayen aur Vikas",
"question_en": "What is the name of the project aimed at developing the Thar Desert region of Rajasthan?",
"question_hi": "राजस्थान के थार मरुस्थल क्षेत्र के विकास के लिए किस परियोजना का नाम है?",
"A_en": "Thar Desert Development Project", "A_hi": "थार मरुस्थल विकास परियोजना",
"B_en": "Rajasthan Desert Development Project", "B_hi": "राजस्थान मरुस्थल विकास परियोजना",
"C_en": "Indira Gandhi Thar Desert Development Project", "C_hi": "इन्दिरा गांधी थार मरुस्थल विकास परियोजना",
"D_en": "Marusthal Vikas Project", "D_hi": "मरुस्थल विकास परियोजना",
"answer": "C",
"explanation_en": "The Indira Gandhi Thar Desert Development Project aims at developing the Thar Desert region of Rajasthan.",
"explanation_hi": "इन्दिरा गांधी थार मरुस्थल विकास परियोजना राजस्थान के थार मरुस्थल क्षेत्र के विकास के लिए है।"
},
{
"subject": "Rajasthan Geography",
"topic": "Thar Marusthal: Visheshatayen aur Vikas",
"question_en": "Which of the following animals is commonly found in the Thar Desert region of Rajasthan?",
"question_hi": "राजस्थान के थार मरुस्थल क्षेत्र में निम्नलिखित में से कौन सा जानवर आमतौर पर पाया जाता है?",
"A_en": "Lion", "A_hi": "शेर",
"B_en": "Tiger", "B_hi": "बाघ",
"C_en": "Camel", "C_hi": "ऊंट",
"D_en": "Elephant", "D_hi": "हाथी",
"answer": "C",
"explanation_en": "The camel is commonly found in the Thar Desert region of Rajasthan.",
"explanation_hi": "ऊंट राजस्थान के थार मरुस्थल क्षेत्र में आमतौर पर पाया जाता है।"
}
]